LICENSE.txt
MANIFEST.in
README.rst
contributors.txt
setup.cfg
setup.py
scodeu/__init__.py
scodeu/client.py
scodeu/familias.py
scodeu.egg-info/PKG-INFO
scodeu.egg-info/SOURCES.txt
scodeu.egg-info/dependency_links.txt
scodeu.egg-info/entry_points.txt
scodeu.egg-info/not-zip-safe
scodeu.egg-info/pbr.json
scodeu.egg-info/requires.txt
scodeu.egg-info/top_level.txt
scodeu/test/__init__.py
scodeu/test/tests.py