Metadata-Version: 1.0
Name: scodeu
Version: 0.3
Summary: 'Search client for OpenData Euskadi'
Home-page: UNKNOWN
Author: Aitzol Naberan
Author-email: anaberan@codesyntax.com
License: GPL
Keywords: 'opendata client search'
Platform: UNKNOWN
